{"version":"1.0.0","last_rebuild":"2026-05-03T23:58:32.507050+00:00","source":"publish_to_gateway.py","endpoints":["coaching-intelligence","product-certifications","rep-performance","sales-kpi","trajectory","training-progress","calibration","coaching-effectiveness","selling-gm","prospecting-effectiveness","pie-prospects","pie-data-nn","pie-data-cs","pie-data-aff","rep-hygiene-deals","rep-forecast-data","forecast-history","forecast-deals","weekly-history","coaching-action-tracker","company-quota","team-quotas","company-budget","forecast-summary","sfdc-rep-summary","sfdc-pipeline","pie-follow-ups","daily-activity-metrics","pie-feedback-log","sfdc-contacts"],"file_count":29}